dlsopticscore/__init__.py
dlsopticscore/analysis/__init__.py
dlsopticscore/analysis/image.py
dlsopticscore/analysis/peakfitting.py
dlsopticscore/analysis/pencilbeamscan.py
dlsopticscore/analysis/pgmcalibration.py
dlsopticscore/analysis/functions/plane.py
dlsopticscore/beam/__init__.py
dlsopticscore/beam/beam.py
dlsopticscore/beam/image.py
dlsopticscore/beam/polarization.py
dlsopticscore/beam/ray.py
dlsopticscore/components/__init__.py
dlsopticscore/components/beamline.py
dlsopticscore/components/element.py
dlsopticscore/components/ellipsoid_mirror.py
dlsopticscore/components/grating.py
dlsopticscore/components/mirror.py
dlsopticscore/components/paraboloid_mirror.py
dlsopticscore/components/pgm.py
dlsopticscore/components/polarimeter.py
dlsopticscore/components/undulator.py
dlsopticscore/geometry/__init__.py
dlsopticscore/geometry/plane.py
dlsopticscore/geometry/point3d.py
dlsopticscore/geometry/ray3d.py
dlsopticscore/geometry/shapes.py
dlsopticscore/geometry/vector2d.py
dlsopticscore/geometry/vector3d.py
dlsopticscore/io/__init__.py
dlsopticscore/io/nexus.py
dlsopticscore/io/scanlist.py
dlsopticscore/io/scans2d.py
dlsopticscore/io/shadow.py
dlsopticscore/utilities/__init__.py
dlsopticscore/utilities/converter.py
dlsopticscore/visualization/__init__.py
dlsopticscore/visualization/lineplot.py
dlsopticscore/visualization/polarizationvisualizer.py
dlsopticscore/visualization/shadowplot.py
dlsopticscore-0.1.1.dist-info/METADATA
dlsopticscore-0.1.1.dist-info/WHEEL
dlsopticscore-0.1.1.dist-info/top_level.txt
dlsopticscore-0.1.1.dist-info/RECORD
