Metadata-Version: 2.1
Name: dlsopticscore
Version: 0.1.1
Summary: A collection of functions and methods for calculations and analysis related to X-ray optical design.
Author-email: Matthew Hand <matthew.hand@diamond.ac.uk>
Requires-Dist: h5py >=2.10.0
Requires-Dist: lmfit >=1.0.0
Requires-Dist: matplotlib >=3.2.1
Requires-Dist: numpy >=1.18.2
Requires-Dist: pandas >=1.0.3
Requires-Dist: Pillow >=7.0.0
Requires-Dist: scipy >=1.10
Provides-Extra: dev
Requires-Dist: flake8 ; extra == 'dev'
Requires-Dist: pytest ; extra == 'dev'
